main.py
app/__init__.py
app/__main__.py
app/add.py
app/check.py
app/config.py
app/constants.py
app/data.py
app/remove.py
app/renew.py
app/update.py
friendly_reminder-1.0.0.dist-info/COPYING
friendly_reminder-1.0.0.dist-info/METADATA
friendly_reminder-1.0.0.dist-info/WHEEL
friendly_reminder-1.0.0.dist-info/entry_points.txt
friendly_reminder-1.0.0.dist-info/top_level.txt
friendly_reminder-1.0.0.dist-info/RECORD
