Metadata-Version: 2.1
Name: friendly-reminder
Version: 1.0.0
Summary: A CLI tool to stay on touch with your friends
Home-page: https://github.com/rluetzner/friendly-reminder
Author: Robert Lützner
Author-email: robert.luetzner@pm.me
License: GPL-3.0
Platform: UNKNOWN
Classifier: Programming Language :: Python :: 3.6
Classifier: Operating System :: OS Independent
Requires-Python: >=3.6
Requires-Dist: PyYAML (==6.0)
Requires-Dist: click (==8.0.4)
Requires-Dist: jsonpickle (==2.1.0)
